freertos_gdb/__init__.py
freertos_gdb/common.py
freertos_gdb/queue.py
freertos_gdb/task.py
freertos_gdb/timer.py
freertos_gdb-1.0.2.dist-info/LICENSE
freertos_gdb-1.0.2.dist-info/METADATA
freertos_gdb-1.0.2.dist-info/WHEEL
freertos_gdb-1.0.2.dist-info/top_level.txt
freertos_gdb-1.0.2.dist-info/RECORD
