Metadata-Version: 2.1
Name: freertos-gdb
Version: 1.0.2
Summary: Python module for operating with freeRTOS-kernel objects in GDB
Home-page: https://github.com/espressif/freertos-gdb
Author: alexey.lapshin
Author-email: alexey.lapshin@espressif.com
License: Apache License 2.0
Project-URL: Bug Tracker, https://github.com/espressif/freertos-gdb/issues
Platform: UNKNOWN
Classifier: Development Status :: 4 - Beta
Classifier: Intended Audience :: Developers
Classifier: Natural Language :: English
Classifier: License :: OSI Approved :: Apache Software License
Classifier: Programming Language :: Python
Classifier: Programming Language :: Python :: 3
Classifier: Programming Language :: Python :: 3.6
Classifier: Programming Language :: Python :: 3.7
Classifier: Programming Language :: Python :: 3.8
Classifier: Programming Language :: Python :: 3.9
Classifier: Programming Language :: Python :: 3.10
Classifier: Programming Language :: Python :: 3 :: Only
Classifier: Programming Language :: Python :: Implementation :: CPython
Requires-Python: >=3.6
License-File: LICENSE
